aionlib/__init__.py
aionlib/_utils.py
aionlib/acph.py
aionlib/config.py
aionlib/language.py
aionlib/logging.py
aionlib/plugin.py
aionlib/skill.py
aionlib/utils.py
aionlib/variable.py
aionlib-0.1.1.dist-info/METADATA
aionlib-0.1.1.dist-info/WHEEL
aionlib-0.1.1.dist-info/top_level.txt
aionlib-0.1.1.dist-info/RECORD
