Metadata-Version: 2.1
Name: aionlib
Version: 0.1.1
Summary: Library support for the 'aion' project
Home-page: https://www.github.com/blueShard-dev/aionlib
Author: blueShard
License: MPL-2.0
Platform: UNKNOWN
Classifier: Development Status :: 4 - Beta
Classifier: Environment :: Console
Classifier: License :: OSI Approved :: Mozilla Public License 2.0 (MPL 2.0)
Classifier: Operating System :: Unix
Classifier: Programming Language :: Python :: 3.6
Classifier: Programming Language :: Python :: 3.7
Classifier: Programming Language :: Python :: 3.8
Classifier: Programming Language :: Python :: 3.9
Classifier: Topic :: Home Automation
Requires-Python: >=3.6.*
Requires-Dist: colorama
